{
  "name": "no_mitigation",
  "data": [
    {
      "seriesName": "AGRCO2N",
      "seriesValues": [
        [
          2018,
          646.395099676456
        ],
        [
          2019,
          1292.817048336783
        ],
        [
          2020,
          1942.3723273308728
        ],
        [
          2021,
          2598.7449486264577
        ],
        [
          2022,
          3238.009504333673
        ],
        [
          2023,
          3875.84996025241
        ],
        [
          2024,
          4511.654935054875
        ],
        [
          2025,
          5146.217597507983
        ],
        [
          2026,
          5778.416692897798
        ],
        [
          2027,
          6409.085640860307
        ],
        [
          2028,
          7040.334119974785
        ],
        [
          2029,
          7803.371473750007
        ],
        [
          2030,
          8564.368334420484
        ],
        [
          2031,
          9322.624665773043
        ],
        [
          2032,
          10076.595106425684
        ],
        [
          2033,
          10827.5762350312
        ],
        [
          2034,
          11575.582495473136
        ],
        [
          2035,
          12320.057739159507
        ],
        [
          2036,
          13061.556101109602
        ],
        [
          2037,
          13800.083642038406
        ],
        [
          2038,
          14541.288968038576
        ],
        [
          2039,
          15279.210031099412
        ],
        [
          2040,
          16014.131723367254
        ],
        [
          2041,
          16746.095378539
        ],
        [
          2042,
          17475.20822432294
        ],
        [
          2043,
          18201.474888060304
        ],
        [
          2044,
          18924.458148593156
        ],
        [
          2045,
          19644.10541932038
        ],
        [
          2046,
          20360.496854593763
        ],
        [
          2047,
          21074.122731534277
        ],
        [
          2048,
          21784.985939135346
        ],
        [
          2049,
          22493.089325356523
        ],
        [
          2050,
          23198.43571701873
        ]
      ]
    },
    {
      "seriesName": "INDCO2N",
      "seriesValues": [
        [
          2018,
          3938.55278615176
        ],
        [
          2019,
          7804.56283063436
        ],
        [
          2020,
          11549.87492677811
        ],
        [
          2021,
          15401.40397913613
        ],
        [
          2022,
          19544.44006175752
        ],
        [
          2023,
          23769.067741282608
        ],
        [
          2024,
          28076.38901527241
        ],
        [
          2025,
          32467.659301601307
        ],
        [
          2026,
          36944.3039319722
        ],
        [
          2027,
          41460.41755925666
        ],
        [
          2028,
          46015.87591886187
        ],
        [
          2029,
          50610.7152484916
        ],
        [
          2030,
          55244.97021315772
        ],
        [
          2031,
          59918.832440122846
        ],
        [
          2032,
          64642.90660719393
        ],
        [
          2033,
          69417.47523683812
        ],
        [
          2034,
          74242.8643592283
        ],
        [
          2035,
          79119.37296806302
        ],
        [
          2036,
          84047.2989396031
        ],
        [
          2037,
          89024.23724084631
        ],
        [
          2038,
          94050.44764147513
        ],
        [
          2039,
          99126.16215255935
        ],
        [
          2040,
          104251.60824499051
        ],
        [
          2041,
          109427.02445448442
        ],
        [
          2042,
          114650.71888071486
        ],
        [
          2043,
          119922.87780209443
        ],
        [
          2044,
          125243.62416512564
        ],
        [
          2045,
          130613.08450176082
        ],
        [
          2046,
          136031.4011845049
        ],
        [
          2047,
          141498.72839648795
        ],
        [
          2048,
          147015.20373005557
        ],
        [
          2049,
          152580.93032327818
        ],
        [
          2050,
          158196.03810964918
        ]
      ]
    },
    {
      "seriesName": "INDCO2P",
      "seriesValues": [
        [
          2018,
          2295.03666588256
        ],
        [
          2019,
          4246.64614645113
        ],
        [
          2020,
          6409.83596022017
        ],
        [
          2021,
          8835.95774288111
        ],
        [
          2022,
          11344.70171082892
        ],
        [
          2023,
          13883.413290495919
        ],
        [
          2024,
          16454.50416054872
        ],
        [
          2025,
          19078.84293877496
        ],
        [
          2026,
          21766.21067003864
        ],
        [
          2027,
          24420.54362940941
        ],
        [
          2028,
          27047.023741145407
        ],
        [
          2029,
          29645.76628033377
        ],
        [
          2030,
          32216.954040115288
        ],
        [
          2031,
          34872.666549276
        ],
        [
          2032,
          37453.97961750216
        ],
        [
          2033,
          40032.61111442023
        ],
        [
          2034,
          42608.75219250483
        ],
        [
          2035,
          45181.09270472428
        ],
        [
          2036,
          47748.975199941706
        ],
        [
          2037,
          50306.25218159106
        ],
        [
          2038,
          52852.53111574201
        ],
        [
          2039,
          55386.730506115106
        ],
        [
          2040,
          57908.278084006546
        ],
        [
          2041,
          60808.622168543036
        ],
        [
          2042,
          64087.91815215008
        ],
        [
          2043,
          67750.05218102873
        ],
        [
          2044,
          71798.94069362993
        ],
        [
          2045,
          76238.53063125911
        ],
        [
          2046,
          80562.82203949626
        ],
        [
          2047,
          84770.55273513078
        ],
        [
          2048,
          88860.38019915312
        ],
        [
          2049,
          92830.95103172994
        ],
        [
          2050,
          96680.90087497416
        ]
      ]
    },
    {
      "seriesName": "PWRCO2N",
      "seriesValues": [
        [
          2018,
          11800.6774638175
        ],
        [
          2019,
          22055.112910292497
        ],
        [
          2020,
          32277.5514356572
        ],
        [
          2021,
          43526.5826672579
        ],
        [
          2022,
          57627.3754061952
        ],
        [
          2023,
          70561.5962711733
        ],
        [
          2024,
          85113.9383626762
        ],
        [
          2025,
          97555.8307661479
        ],
        [
          2026,
          109852.87979937589
        ],
        [
          2027,
          118683.59401517772
        ],
        [
          2028,
          127847.51141761358
        ],
        [
          2029,
          137025.63041653926
        ],
        [
          2030,
          146148.7208044059
        ],
        [
          2031,
          155268.8041362816
        ],
        [
          2032,
          163458.37484822105
        ],
        [
          2033,
          171053.66502429583
        ],
        [
          2034,
          178268.39954154854
        ],
        [
          2035,
          185228.3177431326
        ],
        [
          2036,
          192350.39475687718
        ],
        [
          2037,
          199280.1219406606
        ],
        [
          2038,
          206185.90003620813
        ],
        [
          2039,
          212850.62697143384
        ],
        [
          2040,
          218659.90613906665
        ],
        [
          2041,
          224586.2086562334
        ],
        [
          2042,
          231084.26290167918
        ],
        [
          2043,
          237904.70095098898
        ],
        [
          2044,
          244305.1417016385
        ],
        [
          2045,
          250876.3254512229
        ],
        [
          2046,
          258315.49917889608
        ],
        [
          2047,
          264992.7805768503
        ],
        [
          2048,
          270951.0347005896
        ],
        [
          2049,
          276820.19486341526
        ],
        [
          2050,
          286156.0479156505
        ]
      ]
    },
    {
      "seriesName": "RSDCO2",
      "seriesValues": [
        [
          2018,
          7046.35707780589
        ],
        [
          2019,
          13484.03045387243
        ],
        [
          2020,
          19720.30878648903
        ],
        [
          2021,
          26106.26615591397
        ],
        [
          2022,
          32306.61270358122
        ],
        [
          2023,
          38209.716604251444
        ],
        [
          2024,
          44006.20849496099
        ],
        [
          2025,
          49656.67307839092
        ],
        [
          2026,
          55097.86609707771
        ],
        [
          2027,
          60472.8658194452
        ],
        [
          2028,
          65785.2336820584
        ],
        [
          2029,
          71038.76911499315
        ],
        [
          2030,
          76271.23695066087
        ],
        [
          2031,
          81478.86123350885
        ],
        [
          2032,
          86692.83183454454
        ],
        [
          2033,
          91991.59903959402
        ],
        [
          2034,
          97289.21900498166
        ],
        [
          2035,
          102570.1419489815
        ],
        [
          2036,
          107834.36915090254
        ],
        [
          2037,
          113100.17416111482
        ],
        [
          2038,
          118374.79727527298
        ],
        [
          2039,
          123523.42747957114
        ],
        [
          2040,
          128621.78716145299
        ],
        [
          2041,
          133662.91520383747
        ],
        [
          2042,
          138645.70909702327
        ],
        [
          2043,
          143533.52456617382
        ],
        [
          2044,
          148369.99599264207
        ],
        [
          2045,
          153151.18517896876
        ],
        [
          2046,
          157879.3568840927
        ],
        [
          2047,
          162553.01598108094
        ],
        [
          2048,
          167183.87784246283
        ],
        [
          2049,
          171759.839427881
        ],
        [
          2050,
          176270.21599885618
        ]
      ]
    },
    {
      "seriesName": "SRVCO2N",
      "seriesValues": [
        [
          2018,
          1479.83736929787
        ],
        [
          2019,
          2933.52829006107
        ],
        [
          2020,
          4410.3169828441805
        ],
        [
          2021,
          5865.55808099502
        ],
        [
          2022,
          7836.66690194219
        ],
        [
          2023,
          9996.3500739805
        ],
        [
          2024,
          12412.937898069711
        ],
        [
          2025,
          14885.86667512516
        ],
        [
          2026,
          17410.46115724519
        ],
        [
          2027,
          19937.18934186268
        ],
        [
          2028,
          22499.1193026472
        ],
        [
          2029,
          25118.262932469
        ],
        [
          2030,
          27764.956515249833
        ],
        [
          2031,
          30131.904793357822
        ],
        [
          2032,
          32649.62001455545
        ],
        [
          2033,
          35109.59532836338
        ],
        [
          2034,
          37473.02473050392
        ],
        [
          2035,
          39764.76769533633
        ],
        [
          2036,
          41982.10160138179
        ],
        [
          2037,
          44173.86805725559
        ],
        [
          2038,
          46373.03385165189
        ],
        [
          2039,
          48505.78495399351
        ],
        [
          2040,
          50596.78810124607
        ],
        [
          2041,
          52641.18615048851
        ],
        [
          2042,
          54639.84405175698
        ],
        [
          2043,
          56667.86327341551
        ],
        [
          2044,
          58641.713717518855
        ],
        [
          2045,
          60544.388531324534
        ],
        [
          2046,
          62389.05795883711
        ],
        [
          2047,
          64175.54383653222
        ],
        [
          2048,
          65742.596145773
        ],
        [
          2049,
          66720.86012306719
        ],
        [
          2050,
          67629.1027228187
        ]
      ]
    },
    {
      "seriesName": "TRACO2N",
      "seriesValues": [
        [
          2018,
          11759.335462843927
        ],
        [
          2019,
          23586.032790686037
        ],
        [
          2020,
          33395.960459873924
        ],
        [
          2021,
          44082.81913133394
        ],
        [
          2022,
          55070.795715637745
        ],
        [
          2023,
          66169.7208406078
        ],
        [
          2024,
          77294.95297770576
        ],
        [
          2025,
          88474.84941160349
        ],
        [
          2026,
          99668.97975190316
        ],
        [
          2027,
          110905.50281718902
        ],
        [
          2028,
          122251.9745978317
        ],
        [
          2029,
          133620.9042922397
        ],
        [
          2030,
          144959.64885386112
        ],
        [
          2031,
          156240.582672732
        ],
        [
          2032,
          167343.17975464533
        ],
        [
          2033,
          178027.94756961433
        ],
        [
          2034,
          187698.73841746035
        ],
        [
          2035,
          196337.14733259188
        ],
        [
          2036,
          204459.01594278563
        ],
        [
          2037,
          212330.64830704877
        ],
        [
          2038,
          219660.10628739174
        ],
        [
          2039,
          226913.57136014116
        ],
        [
          2040,
          234075.72878816834
        ],
        [
          2041,
          241080.63910481968
        ],
        [
          2042,
          247968.53079429563
        ],
        [
          2043,
          255116.6955891064
        ],
        [
          2044,
          261486.8770573591
        ],
        [
          2045,
          267591.7684353985
        ],
        [
          2046,
          272612.1468673096
        ],
        [
          2047,
          277093.41836937424
        ],
        [
          2048,
          280984.6028350014
        ],
        [
          2049,
          284489.820987649
        ],
        [
          2050,
          287705.158694378
        ]
      ]
    }
  ]
}