{
  "name": "mitigation_cb_nodh-i",
  "data": [
    {
      "seriesName": "RSDAHT",
      "seriesValues": [
        [
          2018,
          0.3883736806142188
        ],
        [
          2019,
          0.368954996583507
        ],
        [
          2020,
          0.3495363125527968
        ],
        [
          2021,
          0.3301176285220852
        ],
        [
          2022,
          0.310698944491374
        ],
        [
          2023,
          0.357706207892601
        ],
        [
          2024,
          0.40503553649349844
        ],
        [
          2025,
          0.4526933715980594
        ],
        [
          2026,
          0.5006862833363572
        ],
        [
          2027,
          0.5490209732410671
        ],
        [
          2028,
          0.5977042768755149
        ],
        [
          2029,
          0.6467431665142981
        ],
        [
          2030,
          0.6961447538775019
        ],
        [
          2031,
          0.7459162929196153
        ],
        [
          2032,
          0.7960651826742167
        ],
        [
          2033,
          0.846598970155556
        ],
        [
          2034,
          0.8975253533181672
        ],
        [
          2035,
          0.9488521840756756
        ],
        [
          2036,
          1.000587471379981
        ],
        [
          2037,
          1.0527393843620194
        ],
        [
          2038,
          1.105316255535345
        ],
        [
          2039,
          1.1274225806460516
        ],
        [
          2040,
          1.1499710322589727
        ],
        [
          2041,
          1.1729704529041527
        ],
        [
          2042,
          1.1964298619622353
        ],
        [
          2043,
          1.2203584592014804
        ],
        [
          2044,
          1.2447656283855095
        ],
        [
          2045,
          1.2696609409532202
        ],
        [
          2046,
          1.2950541597722844
        ],
        [
          2047,
          1.3209552429677305
        ],
        [
          2048,
          1.3473743478270848
        ],
        [
          2049,
          1.3743218347836268
        ],
        [
          2050,
          1.4018082714792994
        ]
      ]
    },
    {
      "seriesName": "RSDAHT2",
      "seriesValues": [
        [
          2018,
          0.6180800683545399
        ],
        [
          2019,
          0.5871760649368132
        ],
        [
          2020,
          0.5562720615190868
        ],
        [
          2021,
          0.5253680581013581
        ],
        [
          2022,
          0.4944640546836311
        ],
        [
          2023,
          0.4635600512659032
        ],
        [
          2024,
          0.432656047848176
        ],
        [
          2025,
          0.4017520444304496
        ],
        [
          2026,
          0.370848041012722
        ],
        [
          2027,
          0.3399440375949954
        ],
        [
          2028,
          0.3090400341772675
        ],
        [
          2029,
          0.2781360307595414
        ],
        [
          2030,
          0.2472320273418125
        ],
        [
          2031,
          0.2163280239240849
        ],
        [
          2032,
          0.1854240205063582
        ],
        [
          2033,
          0.15452001708863058
        ],
        [
          2034,
          0.1236160136709035
        ],
        [
          2035,
          0.09271201025317698
        ],
        [
          2036,
          0.06180800683544883
        ],
        [
          2037,
          0.030904003417722484
        ]
      ]
    },
    {
      "seriesName": "RSDBDL",
      "seriesValues": [
        [
          2018,
          0.0002723195345893026
        ],
        [
          2019,
          0.0001506670831593624
        ],
        [
          2020,
          0.0001536804248225497
        ],
        [
          2021,
          0.0001567540333190008
        ],
        [
          2022,
          0.0001598891139853807
        ],
        [
          2023,
          0.0001630868962650884
        ],
        [
          2024,
          0.00016634863419039012
        ],
        [
          2025,
          0.00016967560687419789
        ],
        [
          2026,
          5.7089875140042595e-05
        ],
        [
          2027,
          5.82316726428435e-05
        ],
        [
          2028,
          5.93963060957003e-05
        ],
        [
          2029,
          6.058423221761438e-05
        ],
        [
          2030,
          6.17959168619667e-05
        ],
        [
          2031,
          6.30318351992059e-05
        ],
        [
          2032,
          6.429247190319011e-05
        ],
        [
          2033,
          6.557832134125391e-05
        ],
        [
          2034,
          5.4463906917860563e-05
        ],
        [
          2035,
          4.084793018839544e-05
        ],
        [
          2036,
          2.723195345893026e-05
        ],
        [
          2037,
          1.361597672946512e-05
        ]
      ]
    },
    {
      "seriesName": "RSDCOA",
      "seriesValues": [
        [
          2018,
          9.09999999999999
        ],
        [
          2019,
          7.800000000000001
        ],
        [
          2020,
          8.200000000000003
        ],
        [
          2021,
          7.7999999999999945
        ],
        [
          2022,
          6.34
        ],
        [
          2023,
          5.1719999999999935
        ],
        [
          2024,
          4.237599999999999
        ],
        [
          2025,
          3.4900799999999963
        ],
        [
          2026,
          2.892063999999996
        ],
        [
          2027,
          2.4136511999999968
        ],
        [
          2028,
          2.030920960000005
        ],
        [
          2029,
          1.7247367679999954
        ],
        [
          2030,
          1.4797894144000014
        ],
        [
          2031,
          1.2838315315200035
        ],
        [
          2032,
          1.1270652252160045
        ],
        [
          2033,
          1.0016521801728004
        ],
        [
          2034,
          0.9013217441382402
        ],
        [
          2035,
          0.8210573953105922
        ],
        [
          2036,
          0.7568459162484741
        ],
        [
          2037,
          0.7054767329987791
        ],
        [
          2038,
          0.664381386399023
        ],
        [
          2039,
          0.631505109119219
        ],
        [
          2040,
          0.605204087295375
        ],
        [
          2041,
          0.5841632698363
        ],
        [
          2042,
          0.56733061586904
        ],
        [
          2043,
          0.553864492695232
        ],
        [
          2044,
          0.543091594156186
        ],
        [
          2045,
          0.534473275324948
        ],
        [
          2046,
          0.527578620259959
        ],
        [
          2047,
          0.522062896207967
        ],
        [
          2048,
          0.517650316966374
        ],
        [
          2049,
          0.514120253573099
        ],
        [
          2050,
          0.511296202858479
        ]
      ]
    },
    {
      "seriesName": "RSDELC",
      "seriesValues": [
        [
          2018,
          4.468405445916887
        ],
        [
          2019,
          4.709629474842783
        ],
        [
          2020,
          4.985532411118658
        ],
        [
          2021,
          4.605161496307141
        ],
        [
          2022,
          4.765891915760682
        ],
        [
          2023,
          2.0666584472044534
        ],
        [
          2024,
          1.582069481937421
        ],
        [
          2025,
          2.8362607429749764
        ],
        [
          2026,
          5.000377456588254
        ],
        [
          2027,
          7.3709845691313
        ],
        [
          2028,
          9.67338059908633
        ],
        [
          2029,
          9.755357373277189
        ],
        [
          2030,
          9.71114617974899
        ],
        [
          2031,
          12.826041498276261
        ],
        [
          2032,
          15.954352322013403
        ],
        [
          2033,
          17.223398837350743
        ],
        [
          2034,
          18.493823561655482
        ],
        [
          2035,
          19.732236312852184
        ],
        [
          2036,
          20.972716516351557
        ],
        [
          2037,
          22.21128997735994
        ],
        [
          2038,
          23.50311666141259
        ],
        [
          2039,
          25.84973097059003
        ],
        [
          2040,
          27.21575171813932
        ],
        [
          2041,
          27.878815526572097
        ],
        [
          2042,
          28.707298853732908
        ],
        [
          2043,
          29.059088079406685
        ],
        [
          2044,
          29.268765075176063
        ],
        [
          2045,
          29.65609560665524
        ],
        [
          2046,
          30.000067688216728
        ],
        [
          2047,
          30.23962556621869
        ],
        [
          2048,
          30.251442354946672
        ],
        [
          2049,
          30.248856012478893
        ],
        [
          2050,
          30.235799433976105
        ]
      ]
    },
    {
      "seriesName": "RSDETH",
      "seriesValues": [
        [
          2018,
          0.00015597481966388098
        ],
        [
          2019,
          0.00014817607868068688
        ],
        [
          2020,
          6.64919445341997e-05
        ],
        [
          2021,
          6.924638534357116e-05
        ],
        [
          2022,
          7.617102387792833e-05
        ],
        [
          2023,
          8.378812626572126e-05
        ],
        [
          2024,
          9.216693889229331e-05
        ],
        [
          2025,
          0.00010138363278152268
        ],
        [
          2026,
          9.357355893760039e-05
        ],
        [
          2027,
          8.57757623594671e-05
        ],
        [
          2028,
          7.79779657813336e-05
        ],
        [
          2029,
          7.01801692032002e-05
        ],
        [
          2030,
          6.23823726250669e-05
        ],
        [
          2031,
          5.458457604693356e-05
        ],
        [
          2032,
          4.678677946880022e-05
        ],
        [
          2033,
          3.898898289066689e-05
        ],
        [
          2034,
          3.11911863125335e-05
        ],
        [
          2035,
          2.339338973440005e-05
        ],
        [
          2036,
          1.559559315626673e-05
        ],
        [
          2037,
          7.79779657813336e-06
        ]
      ]
    },
    {
      "seriesName": "RSDGAS",
      "seriesValues": [
        [
          2018,
          25.44517685415292
        ],
        [
          2019,
          24.799999999999997
        ],
        [
          2020,
          25.1979990417283
        ],
        [
          2021,
          24.999999999999993
        ],
        [
          2022,
          25.599999999999994
        ],
        [
          2023,
          26.1619425193922
        ],
        [
          2024,
          26.737169930525628
        ],
        [
          2025,
          27.373894730525635
        ],
        [
          2026,
          28.023354026525624
        ],
        [
          2027,
          28.68580250844563
        ],
        [
          2028,
          29.361499960004036
        ],
        [
          2029,
          30.05071136059362
        ],
        [
          2030,
          30.75370698919498
        ],
        [
          2031,
          25.925154273278217
        ],
        [
          2032,
          22.60849469662767
        ],
        [
          2033,
          21.686625028565857
        ],
        [
          2034,
          20.76666163115563
        ],
        [
          2035,
          19.850261137557492
        ],
        [
          2036,
          18.937258765702833
        ],
        [
          2037,
          18.025046583074314
        ],
        [
          2038,
          17.148577631246127
        ],
        [
          2039,
          15.286421874841757
        ],
        [
          2040,
          14.098089057115654
        ],
        [
          2041,
          13.596468293221953
        ],
        [
          2042,
          13.138923100159957
        ],
        [
          2043,
          12.799153472435169
        ],
        [
          2044,
          12.472888092152491
        ],
        [
          2045,
          11.814344546979891
        ],
        [
          2046,
          11.2505332112944
        ],
        [
          2047,
          10.778234154631502
        ],
        [
          2048,
          10.567584304292314
        ],
        [
          2049,
          10.355617760841255
        ],
        [
          2050,
          10.145214099029145
        ]
      ]
    },
    {
      "seriesName": "RSDHET_Apt",
      "seriesValues": [
        [
          2018,
          0.05462012276356143
        ],
        [
          2019,
          0.15133696182218648
        ],
        [
          2020,
          0.2394283917429388
        ],
        [
          2022,
          0.10234621764678661
        ],
        [
          2023,
          0.10296687722444467
        ],
        [
          2024,
          0.10358753680210402
        ],
        [
          2025,
          0.10420819637976307
        ],
        [
          2026,
          0.1048288559574223
        ],
        [
          2027,
          0.10544951553508201
        ],
        [
          2028,
          0.10607017511274086
        ],
        [
          2029,
          0.10669083469039975
        ],
        [
          2030,
          0.10731149426805874
        ],
        [
          2031,
          0.10793215384571878
        ],
        [
          2032,
          0.1085528134233774
        ],
        [
          2033,
          0.1091734730010365
        ],
        [
          2034,
          0.10979413257869561
        ],
        [
          2035,
          0.11041479215635477
        ],
        [
          2036,
          0.11103545173401433
        ],
        [
          2037,
          0.11165611131167304
        ],
        [
          2038,
          0.1122767708893329
        ],
        [
          2039,
          0.1128974304669914
        ],
        [
          2040,
          0.1081954722114702
        ],
        [
          2041,
          0.06519142476628685
        ]
      ]
    },
    {
      "seriesName": "RSDHET_Att",
      "seriesValues": [
        [
          2018,
          0.05349856460415353
        ],
        [
          2019,
          0.27170984073944665
        ],
        [
          2020,
          0.31794324848269706
        ],
        [
          2022,
          0.18249526398747498
        ],
        [
          2023,
          0.18196521331231424
        ],
        [
          2024,
          0.1814351626371534
        ],
        [
          2025,
          0.18090511196199263
        ],
        [
          2026,
          0.18037506128683192
        ],
        [
          2027,
          0.1798450106116715
        ],
        [
          2028,
          0.17931495993651084
        ],
        [
          2029,
          0.1787849092613498
        ],
        [
          2030,
          0.17825485858618922
        ],
        [
          2031,
          0.17772480791102846
        ],
        [
          2032,
          0.1771947572358677
        ],
        [
          2033,
          0.17666470656070732
        ],
        [
          2034,
          0.17613465588554647
        ],
        [
          2035,
          0.1756046052103862
        ],
        [
          2036,
          0.17507455453522514
        ],
        [
          2037,
          0.17454450386006476
        ],
        [
          2038,
          0.1740144531849046
        ],
        [
          2039,
          0.1734844025097429
        ],
        [
          2040,
          0.1648448961783181
        ],
        [
          2041,
          0.09848176797196198
        ]
      ]
    },
    {
      "seriesName": "RSDHET_Det",
      "seriesValues": [
        [
          2018,
          0.16899993918420753
        ],
        [
          2019,
          0.31773201398805306
        ],
        [
          2020,
          0.133811887802255
        ],
        [
          2022,
          0.015158518365732742
        ],
        [
          2023,
          0.015067909463233912
        ],
        [
          2024,
          0.014977300560735655
        ],
        [
          2025,
          0.014886691658237826
        ],
        [
          2026,
          0.014796082755739142
        ],
        [
          2027,
          0.014705473853240805
        ],
        [
          2028,
          0.01461486495074283
        ],
        [
          2029,
          0.014524256048244017
        ],
        [
          2030,
          0.01443364714574558
        ],
        [
          2031,
          0.014343038243247447
        ],
        [
          2032,
          0.014252429340748706
        ],
        [
          2033,
          0.014161820438250467
        ],
        [
          2034,
          0.01407121153575213
        ],
        [
          2035,
          0.013980602633253694
        ],
        [
          2036,
          0.013889993730755655
        ],
        [
          2037,
          0.01379938482825712
        ],
        [
          2038,
          0.01370877592575808
        ],
        [
          2039,
          0.013618167023259777
        ],
        [
          2040,
          0.026959631610205523
        ],
        [
          2041,
          0.1363268072617451
        ],
        [
          2042,
          0.29999999999999555
        ],
        [
          2043,
          0.29999999999999644
        ],
        [
          2044,
          0.2999999999999959
        ],
        [
          2045,
          0.2999999999999963
        ],
        [
          2046,
          0.2999999999999968
        ],
        [
          2047,
          0.2999999999999947
        ],
        [
          2048,
          0.2999999999999947
        ],
        [
          2049,
          0.29999999999999516
        ],
        [
          2050,
          0.29999999999999516
        ]
      ]
    },
    {
      "seriesName": "RSDKER",
      "seriesValues": [
        [
          2018,
          50.29999999999998
        ],
        [
          2019,
          49.89999999999997
        ],
        [
          2020,
          48.21201662662565
        ],
        [
          2021,
          51.20000000000006
        ],
        [
          2022,
          51.09275325394572
        ],
        [
          2023,
          45.53156487488485
        ],
        [
          2024,
          44.970025081111444
        ],
        [
          2025,
          42.01771554850949
        ],
        [
          2026,
          38.3484358005708
        ],
        [
          2027,
          34.50651186834826
        ],
        [
          2028,
          30.761543783396576
        ],
        [
          2029,
          29.59539943951494
        ],
        [
          2030,
          28.439333437409577
        ],
        [
          2031,
          27.8645045441552
        ],
        [
          2032,
          27.264795276784728
        ],
        [
          2033,
          26.593409408905266
        ],
        [
          2034,
          25.940199150386384
        ],
        [
          2035,
          25.21998836681727
        ],
        [
          2036,
          24.45895232401138
        ],
        [
          2037,
          23.657529637399456
        ],
        [
          2038,
          22.7358374305117
        ],
        [
          2039,
          20.357516761065668
        ],
        [
          2040,
          18.612908624043946
        ],
        [
          2041,
          16.864984489176635
        ],
        [
          2042,
          15.144123578202079
        ],
        [
          2043,
          14.028073015382398
        ],
        [
          2044,
          12.997430013113718
        ],
        [
          2045,
          12.030751731191195
        ],
        [
          2046,
          11.103390742497657
        ],
        [
          2047,
          10.225085109127681
        ],
        [
          2048,
          9.347876474598152
        ],
        [
          2049,
          8.23899271260886
        ],
        [
          2050,
          7.3164277163995814
        ]
      ]
    },
    {
      "seriesName": "RSDLPG",
      "seriesValues": [
        [
          2018,
          2.2999999999999976
        ],
        [
          2019,
          2.0999999999999965
        ],
        [
          2020,
          2.3999999999999955
        ],
        [
          2021,
          2.099999999999995
        ],
        [
          2022,
          2.283999999999995
        ],
        [
          2023,
          2.4753599999999953
        ],
        [
          2024,
          2.6743743999999983
        ],
        [
          2025,
          2.8813493759999997
        ],
        [
          2026,
          3.0966033510399993
        ],
        [
          2027,
          3.3204674850815987
        ],
        [
          2028,
          3.553286184484864
        ],
        [
          2029,
          3.7954176318642583
        ],
        [
          2030,
          4.047234337138829
        ],
        [
          2031,
          4.309123710624382
        ],
        [
          2032,
          4.581488659049357
        ],
        [
          2033,
          4.864748205411332
        ],
        [
          2034,
          5.159338133627786
        ],
        [
          2035,
          5.4657116589728965
        ],
        [
          2036,
          5.784340125331813
        ],
        [
          2037,
          6.115713730345085
        ],
        [
          2038,
          6.460342279558889
        ],
        [
          2039,
          6.818755970741244
        ],
        [
          2040,
          7.191506209570895
        ],
        [
          2041,
          7.579166457953728
        ],
        [
          2042,
          7.982333116271876
        ],
        [
          2043,
          8.401626440922755
        ],
        [
          2044,
          8.83769149855966
        ],
        [
          2045,
          9.291199158502046
        ],
        [
          2046,
          9.76284712484213
        ],
        [
          2047,
          10.253361009835814
        ],
        [
          2048,
          10.763495450229252
        ],
        [
          2049,
          11.29403526823842
        ],
        [
          2050,
          11.845796678967957
        ]
      ]
    },
    {
      "seriesName": "RSDPEA",
      "seriesValues": [
        [
          2018,
          8.300000000000004
        ],
        [
          2019,
          7.6999999999999975
        ],
        [
          2020,
          8.000000000000002
        ],
        [
          2021,
          7.599999999999997
        ],
        [
          2022,
          6.179999999999996
        ],
        [
          2023,
          5.043999999999995
        ],
        [
          2024,
          4.1351999999999975
        ],
        [
          2025,
          3.4081599999999983
        ],
        [
          2026,
          2.8265280000000006
        ],
        [
          2027,
          2.3612224000000017
        ],
        [
          2028,
          1.9889779200000026
        ],
        [
          2029,
          1.6911823360000018
        ],
        [
          2030,
          1.4529458687999997
        ],
        [
          2031,
          1.262356695039996
        ],
        [
          2032,
          1.1098853560320008
        ],
        [
          2033,
          0.9879082848256
        ],
        [
          2034,
          0.8903266278604802
        ],
        [
          2035,
          0.8122613022883838
        ],
        [
          2036,
          0.7498090418307075
        ],
        [
          2037,
          0.6998472334645662
        ],
        [
          2038,
          0.659877786771653
        ],
        [
          2039,
          0.627902229417322
        ],
        [
          2040,
          0.602321783533858
        ],
        [
          2041,
          0.581857426827086
        ],
        [
          2042,
          0.565485941461669
        ],
        [
          2043,
          0.552388753169335
        ],
        [
          2044,
          0.541911002535468
        ],
        [
          2045,
          0.533528802028375
        ],
        [
          2046,
          0.5268230416227
        ],
        [
          2047,
          0.52145843329816
        ],
        [
          2048,
          0.517166746638528
        ],
        [
          2049,
          0.513733397310822
        ],
        [
          2050,
          0.510986717848658
        ]
      ]
    },
    {
      "seriesName": "RSDSOL",
      "seriesValues": [
        [
          2018,
          0.6000000000000004
        ],
        [
          2019,
          0.5853846656702094
        ],
        [
          2020,
          0.5545749464244094
        ],
        [
          2022,
          0.2000000000000003
        ],
        [
          2023,
          0.4030000000000233
        ],
        [
          2024,
          0.4313360694412073
        ],
        [
          2025,
          0.4005263501954063
        ],
        [
          2026,
          0.3697166309496063
        ],
        [
          2027,
          0.33890691170380616
        ],
        [
          2028,
          0.3080971924580052
        ],
        [
          2029,
          0.2772874732122042
        ],
        [
          2030,
          0.2464777539664042
        ],
        [
          2031,
          0.21566803472060408
        ],
        [
          2032,
          0.1848583154748031
        ],
        [
          2033,
          0.1540485962290025
        ],
        [
          2034,
          0.123238876983202
        ],
        [
          2035,
          0.0924291577374015
        ],
        [
          2036,
          0.061619438491600995
        ],
        [
          2037,
          0.0308097192458005
        ]
      ]
    },
    {
      "seriesName": "RSDWOO",
      "seriesValues": [
        [
          2018,
          1.300000000000001
        ],
        [
          2019,
          1.0999999999999934
        ],
        [
          2020,
          1.099999999999999
        ],
        [
          2021,
          1.1999999999999706
        ],
        [
          2022,
          1.2239999999999995
        ],
        [
          2023,
          0.022404555669620366
        ],
        [
          2024,
          0.009256963599351995
        ],
        [
          2025,
          0.008595751913684023
        ],
        [
          2026,
          0.007934540228015952
        ],
        [
          2027,
          0.0072733285423479815
        ],
        [
          2028,
          0.0026146296204968
        ],
        [
          2029,
          0.0026669222129068
        ],
        [
          2030,
          0.0027202606571649
        ],
        [
          2031,
          0.002420431379573797
        ],
        [
          2032,
          0.002074655468206126
        ],
        [
          2033,
          0.001728879556838455
        ],
        [
          2034,
          0.001383103645470684
        ],
        [
          2035,
          0.001037327734103013
        ],
        [
          2036,
          0.000691551822735342
        ],
        [
          2037,
          0.000345775911367671
        ]
      ]
    }
  ]
}