{
  "name": "mitigation_cb_dhplus-i",
  "data": [
    {
      "seriesName": "FT_IND",
      "seriesValues": [
        [
          2018,
          5.766206340060584
        ],
        [
          2019,
          6.533715932137197
        ],
        [
          2020,
          6.041658300077047
        ],
        [
          2021,
          6.385411793860928
        ],
        [
          2022,
          5.901373580131357
        ],
        [
          2023,
          6.6949820674342275
        ],
        [
          2024,
          6.997136518833256
        ],
        [
          2025,
          7.3619687677920975
        ],
        [
          2026,
          8.304225594493346
        ],
        [
          2027,
          8.668175891742955
        ],
        [
          2028,
          9.036333694619014
        ],
        [
          2029,
          9.408033558200982
        ],
        [
          2030,
          9.782587021897703
        ],
        [
          2031,
          10.094702630674133
        ],
        [
          2032,
          8.796881502537998
        ],
        [
          2033,
          10.813184154490612
        ],
        [
          2034,
          11.181392133517884
        ],
        [
          2035,
          11.555683061093397
        ],
        [
          2036,
          11.939787121689672
        ],
        [
          2037,
          9.450626280147405
        ],
        [
          2038,
          9.557558825123817
        ],
        [
          2039,
          9.664727801046928
        ],
        [
          2040,
          12.875258092892093
        ],
        [
          2041,
          13.264443999893112
        ],
        [
          2042,
          13.645191608453256
        ],
        [
          2043,
          12.310417491647414
        ],
        [
          2044,
          12.701158985580783
        ],
        [
          2045,
          10.280370960383417
        ],
        [
          2046,
          10.3810638791359
        ],
        [
          2047,
          12.91031464149917
        ],
        [
          2048,
          13.38875224753845
        ],
        [
          2049,
          10.8845233574208
        ],
        [
          2050,
          11.0523431835157
        ]
      ]
    },
    {
      "seriesName": "FT_RSD",
      "seriesValues": [
        [
          2023,
          0.0056100390367116
        ],
        [
          2025,
          0.0058366846137947
        ],
        [
          2030,
          0.0031742228663554
        ],
        [
          2031,
          0.0032377073236825
        ],
        [
          2032,
          0.0033024614701561
        ],
        [
          2033,
          0.0033685106995592
        ],
        [
          2034,
          0.0034358809135504
        ],
        [
          2035,
          0.0035045985318214
        ],
        [
          2036,
          0.0035746905024579
        ]
      ]
    },
    {
      "seriesName": "FT_SRV",
      "seriesValues": [
        [
          2025,
          1.278106528
        ],
        [
          2028,
          0.84797147847903
        ],
        [
          2029,
          0.964930908048611
        ],
        [
          2030,
          1.08422952620958
        ],
        [
          2031,
          1.20591411673377
        ],
        [
          2034,
          1.58576570799082
        ],
        [
          2039,
          2.27121749256552
        ],
        [
          2040,
          0.766849587535115
        ],
        [
          2041,
          0.404745941992631
        ],
        [
          2042,
          0.404745941992631
        ],
        [
          2043,
          0.404745941992631
        ],
        [
          2044,
          0.404745941992631
        ]
      ]
    }
  ]
}