{
  "name": "mitigation_cb_dhplus-z",
  "data": [
    {
      "seriesName": "FT_RSD",
      "seriesValues": [
        [
          2018,
          0.0001559748196638
        ],
        [
          2019,
          0.0001481760786806
        ],
        [
          2020,
          6.64919445341997e-05
        ],
        [
          2021,
          6.92463853435712e-05
        ],
        [
          2022,
          7.61710238779283e-05
        ],
        [
          2023,
          8.37881262657212e-05
        ],
        [
          2024,
          9.21669388922933e-05
        ],
        [
          2025,
          0.0001013836327815
        ],
        [
          2026,
          6.44524048197855e-05
        ],
        [
          2027,
          7.08976453017641e-05
        ],
        [
          2028,
          7.79874098319405e-05
        ],
        [
          2029,
          7.01886688487464e-05
        ],
        [
          2030,
          6.23899278655524e-05
        ],
        [
          2031,
          5.45911868823583e-05
        ],
        [
          2032,
          4.67924458991643e-05
        ],
        [
          2033,
          3.89937049159702e-05
        ],
        [
          2034,
          3.11949639327762e-05
        ],
        [
          2035,
          2.33962229495822e-05
        ],
        [
          2036,
          1.55974819663881e-05
        ],
        [
          2037,
          7.79874098319405e-06
        ]
      ]
    },
    {
      "seriesName": "FT_TRA",
      "seriesValues": [
        [
          2018,
          1.15533938504018
        ],
        [
          2019,
          1.1
        ],
        [
          2020,
          0.9
        ],
        [
          2021,
          0.9
        ],
        [
          2022,
          0.0236788076739566
        ],
        [
          2023,
          5.792861348076148
        ],
        [
          2024,
          6.33566976821764
        ],
        [
          2025,
          6.12102545302389
        ],
        [
          2026,
          6.75492610359667
        ],
        [
          2027,
          6.75491965835618
        ],
        [
          2028,
          6.6408112464421505
        ],
        [
          2029,
          6.16491592399369
        ],
        [
          2030,
          5.696564403536601
        ],
        [
          2031,
          5.50458727369313
        ],
        [
          2032,
          5.19560922406518
        ],
        [
          2033,
          4.833764852530985
        ],
        [
          2034,
          4.476689625709198
        ],
        [
          2035,
          4.121327164160441
        ],
        [
          2036,
          3.736707175173165
        ],
        [
          2037,
          3.318027606081778
        ],
        [
          2038,
          2.9089953375067608
        ],
        [
          2039,
          2.503792689597981
        ],
        [
          2040,
          2.096442669718511
        ],
        [
          2041,
          1.679937605500387
        ],
        [
          2042,
          1.286136453478749
        ],
        [
          2043,
          0.962045419799076
        ],
        [
          2044,
          0.717995632957402
        ],
        [
          2045,
          0.512153998303208
        ],
        [
          2046,
          0.425812002632842
        ],
        [
          2047,
          0.40894068091176
        ],
        [
          2048,
          0.406753618224992
        ],
        [
          2049,
          0.404774944227682
        ],
        [
          2050,
          0.403028790070985
        ]
      ]
    }
  ]
}