{
  "name": "mitigation_cb-2070",
  "data": [
    {
      "serieName": "DMD_TRA-F-MTRUCK-ICE",
      "seriesValues": [
        [
          2018,
          11.035
        ],
        [
          2019,
          11.2005
        ],
        [
          2020,
          11.405750000000001
        ],
        [
          2021,
          11.4122420865681
        ],
        [
          2022,
          11.223891563617254
        ],
        [
          2023,
          10.86534895335962
        ],
        [
          2024,
          10.32554260533092
        ],
        [
          2025,
          9.727716189251865
        ],
        [
          2026,
          9.195128637644645
        ],
        [
          2027,
          8.745953682258861
        ],
        [
          2028,
          8.385833403489428
        ],
        [
          2029,
          8.051599128337584
        ],
        [
          2030,
          7.703990043984225
        ],
        [
          2031,
          7.173310865513993
        ],
        [
          2032,
          6.397431794388089
        ],
        [
          2035,
          3.138599817628913
        ],
        [
          2040,
          0.19287870268422722
        ]
      ]
    },
    {
      "serieName": "DMD_TRA-F-MTRUCK-HEV",
      "seriesValues": [
        [
          2022,
          0.0299708301367466
        ],
        [
          2023,
          0.12455648370512
        ],
        [
          2024,
          0.26643496405768
        ],
        [
          2025,
          0.47925268458652
        ],
        [
          2026,
          0.79847926537978
        ],
        [
          2027,
          1.27731913656967
        ],
        [
          2028,
          1.82865045158521
        ],
        [
          2029,
          2.40279862413127
        ],
        [
          2030,
          2.50217335558316
        ],
        [
          2031,
          2.57420281654931
        ],
        [
          2032,
          2.73617787724455
        ],
        [
          2035,
          2.11211077834791
        ],
        [
          2040,
          1.07577723393477
        ],
        [
          2045,
          0.528536783189357
        ],
        [
          2050,
          0.116758500437536
        ]
      ]
    },
    {
      "serieName": "DMD_TRA-F-MTRUCK-BEV",
      "seriesValues": [
        [
          2025,
          0.0796002385
        ],
        [
          2026,
          0.19900059625
        ],
        [
          2027,
          0.378101132875
        ],
        [
          2028,
          0.6467519378125
        ],
        [
          2029,
          1.04972814521875
        ],
        [
          2030,
          1.65419245632813
        ],
        [
          2031,
          2.56088892299219
        ],
        [
          2032,
          3.92093362298828
        ],
        [
          2035,
          10.5777941471844
        ],
        [
          2040,
          18.1362463101116
        ],
        [
          2045,
          21.8533420329595
        ],
        [
          2050,
          24.495442008227
        ]
      ]
    },
    {
      "serieName": "DMD_TRA-F-MTRUCK-FCV",
      "seriesValues": [
        [
          2030,
          0.0796002385
        ],
        [
          2031,
          0.0784294317686746
        ],
        [
          2032,
          0.0743086010329353
        ],
        [
          2035,
          0.0598472300015853
        ],
        [
          2040,
          0.032801327177871
        ],
        [
          2045,
          0.0148373827921312
        ],
        [
          2050,
          0.0059521496520031
        ]
      ]
    }
  ]
}