{
  "name": "mitigation_cb-s10-90",
  "data": [
    {
      "seriesName": "RSD_BLD-XXX_NRGSRV-WS",
      "seriesValues": [
        [
          2018,
          6903.198141993939
        ],
        [
          2019,
          6637.285414980111
        ],
        [
          2020,
          6627.746872925593
        ],
        [
          2021,
          6676.608060203475
        ],
        [
          2022,
          6405.018378326945
        ],
        [
          2023,
          5365.534399060041
        ],
        [
          2024,
          5160.294800373034
        ],
        [
          2025,
          4971.654168302771
        ],
        [
          2026,
          4949.96498428913
        ],
        [
          2027,
          4809.317057068086
        ],
        [
          2028,
          4584.81276766339
        ],
        [
          2029,
          4122.717488504505
        ],
        [
          2030,
          3959.908790197183
        ],
        [
          2031,
          3681.4099061680768
        ],
        [
          2032,
          3487.1809505722204
        ],
        [
          2033,
          3364.4412006805132
        ],
        [
          2034,
          3197.3001937342588
        ],
        [
          2035,
          3033.5503103590368
        ],
        [
          2036,
          2869.371244618599
        ],
        [
          2037,
          2718.1952892315344
        ],
        [
          2038,
          2510.8300788564993
        ],
        [
          2039,
          2235.1812004233616
        ],
        [
          2040,
          1948.5600211783956
        ],
        [
          2041,
          1685.8545230638238
        ],
        [
          2042,
          1410.379287094821
        ],
        [
          2043,
          1332.4799127651659
        ],
        [
          2044,
          1164.9009229667813
        ],
        [
          2045,
          1028.646754234305
        ],
        [
          2046,
          880.6002464129506
        ],
        [
          2047,
          816.1908507692578
        ],
        [
          2048,
          776.7720192900383
        ],
        [
          2049,
          743.0091598469711
        ],
        [
          2050,
          644.6394501575458
        ]
      ]
    },
    {
      "seriesName": "RSD_BLD-XXX_NRGSRV-CK",
      "seriesValues": [
        [
          2023,
          6.45063781137759
        ],
        [
          2024,
          7.45994145676128
        ],
        [
          2025,
          7.45994145676128
        ],
        [
          2026,
          7.45994145676128
        ],
        [
          2027,
          7.45994145676128
        ],
        [
          2028,
          7.45994145676128
        ],
        [
          2029,
          7.45994145676128
        ],
        [
          2030,
          7.45994145676128
        ],
        [
          2031,
          7.45994145676128
        ],
        [
          2032,
          7.45994145676128
        ],
        [
          2033,
          7.45994145676128
        ],
        [
          2034,
          7.45994145676128
        ],
        [
          2035,
          7.45994145676128
        ],
        [
          2036,
          7.45994145676128
        ],
        [
          2037,
          7.45994145676128
        ],
        [
          2038,
          1.00930364538369
        ]
      ]
    }
  ]
}